toil/__init__.py
toil/framework.py
toil/batch/__init__.py
toil/batch/base.py
toil/config/__init__.py
toil/config/config.json
toil/config/util.py
toil/crypto/__init__.py
toil/crypto/symmetric.py
toil/crypto/test_symmetricEncryptor.py
toil/parm/__init__.py
toil/parm/parse.py
toil/provider/__init__.py
toil/provider/aws.py
toil/provider/base.py
toil/provider/chefapi.py
toil/provider/datasource.py
toil/provider/example.py
toil/provider/oci_sdk.py
toil/provider/openstack.py
toil/provider/openstack_sdk.py
toil/provider/policy.py
toil/provider/scalr.py
toil/script/__init__.py
toil/script/toil_config.py
toil/util/__init__.py
toil/util/decorator.py
toil_py-1.3.1.dist-info/METADATA
toil_py-1.3.1.dist-info/RECORD
toil_py-1.3.1.dist-info/WHEEL
toil_py-1.3.1.dist-info/entry_points.txt
toil_py-1.3.1.dist-info/top_level.txt
