Metadata-Version: 2.1
Name: toil-py
Version: 1.3.1
Summary: toil - Hard working python framework with eyes and boots on the ground for your cloud. Built in workers include OCI, AWS, CHEF, SCALR, REALTIONAL DATA SOURCES.
Home-page: https://github.com/drewncrew/toil
Author: Andrew Love
Author-email: DREWNCREW@GMAIL.COM
License: MIT
Keywords: cloud oci aws scalr mysql oracle framework openstack
Platform: UNKNOWN
Classifier: Development Status :: 4 - Beta
Classifier: Intended Audience :: Developers
Classifier: Topic :: Software Development :: Build Tools
Classifier: License :: OSI Approved :: MIT License
Classifier: Programming Language :: Python :: 2.7
Provides-Extra: test
Provides-Extra: dev
Requires-Dist: PyMySQL
Requires-Dist: cryptography (>=2.1.3)
Requires-Dist: SQLAlchemy
Requires-Dist: requests (>=2.5.1)
Requires-Dist: nose
Requires-Dist: urllib3[secure]
Requires-Dist: PyChef
Requires-Dist: oci
Requires-Dist: openstacksdk
Requires-Dist: boto3
Provides-Extra: dev
Requires-Dist: check-manifest; extra == 'dev'
Provides-Extra: test
Requires-Dist: coverage; extra == 'test'
